Metadata-Version: 2.1
Name: pipelinewise-tap-github
Version: 1.1.1
Summary: Singer.io tap for extracting data from the GitHub API
Home-page: https://github.com/transferwise/pipelinewise-tap-github
Author: Wise
Classifier: License :: OSI Approved :: GNU Affero General Public License v3
Classifier: Programming Language :: Python :: 3 :: Only
License-File: LICENSE
Requires-Dist: pipelinewise-singer-python ==1.*
Requires-Dist: requests ==2.20.0
Provides-Extra: test
Requires-Dist: pylint ==2.10.2 ; extra == 'test'
Requires-Dist: pytest ==6.2.4 ; extra == 'test'
